{
  "m_Version": 12,
  "DisplayName": "ZIL 130 Parts",
  "Icon": "Deliver",
  "Color": "FBFCFEFF",
  "InitStockPercent": 75.0,
  "IsExchange": 0,
  "Items": [
	{
      "ClassName": "ZIL_130_ac40_doors_cargo1",
      "MaxPriceThreshold": 5000,
      "MinPriceThreshold": 5000,
      "SellPricePercent": 50.0,
      "MaxStockThreshold": 1,
      "MinStockThreshold": 1,
      "QuantityPercent": -1,
      "SpawnAttachments": [],
      "Variants": []
    },
    {
      "ClassName": "ZIL_130_ac40_doors_cargo2",
      "MaxPriceThreshold": 5000,
      "MinPriceThreshold": 5000,
      "SellPricePercent": 50.0,
      "MaxStockThreshold": 1,
      "MinStockThreshold": 1,
      "QuantityPercent": -1,
      "SpawnAttachments": [],
      "Variants": []
    },
    {
      "ClassName": "ZIL_130_ac40_doors_cargo3",
      "MaxPriceThreshold": 5000,
      "MinPriceThreshold": 5000,
      "SellPricePercent": 50.0,
      "MaxStockThreshold": 1,
      "MinStockThreshold": 1,
      "QuantityPercent": -1,
      "SpawnAttachments": [],
      "Variants": []
    },
    {
      "ClassName": "ZIL_130_ac40_doors_cargo4",
      "MaxPriceThreshold": 5000,
      "MinPriceThreshold": 5000,
      "SellPricePercent": 50.0,
      "MaxStockThreshold": 1,
      "MinStockThreshold": 1,
      "QuantityPercent": -1,
      "SpawnAttachments": [],
      "Variants": []
    },
    {
      "ClassName": "ZIL_130_ac40_doors_codriver",
      "MaxPriceThreshold": 5000,
      "MinPriceThreshold": 5000,
      "SellPricePercent": 50.0,
      "MaxStockThreshold": 1,
      "MinStockThreshold": 1,
      "QuantityPercent": -1,
      "SpawnAttachments": [],
      "Variants": []
    },
    {
      "ClassName": "ZIL_130_ac40_doors_codriver_CHAES",
      "MaxPriceThreshold": 5000,
      "MinPriceThreshold": 5000,
      "SellPricePercent": 50.0,
      "MaxStockThreshold": 1,
      "MinStockThreshold": 1,
      "QuantityPercent": -1,
      "SpawnAttachments": [],
      "Variants": []
    },
    {
      "ClassName": "ZIL_130_ac40_doors_codriver_Chernobyl",
      "MaxPriceThreshold": 5000,
      "MinPriceThreshold": 5000,
      "SellPricePercent": 50.0,
      "MaxStockThreshold": 1,
      "MinStockThreshold": 1,
      "QuantityPercent": -1,
      "SpawnAttachments": [],
      "Variants": []
    },
    {
      "ClassName": "ZIL_130_ac40_doors_codriver_Livonia",
      "MaxPriceThreshold": 5000,
      "MinPriceThreshold": 5000,
      "SellPricePercent": 50.0,
      "MaxStockThreshold": 1,
      "MinStockThreshold": 1,
      "QuantityPercent": -1,
      "SpawnAttachments": [],
      "Variants": []
    },
    {
      "ClassName": "ZIL_130_ac40_doors_codriver_Pripyat",
      "MaxPriceThreshold": 5000,
      "MinPriceThreshold": 5000,
      "SellPricePercent": 50.0,
      "MaxStockThreshold": 1,
      "MinStockThreshold": 1,
      "QuantityPercent": -1,
      "SpawnAttachments": [],
      "Variants": []
    },
	{
      "ClassName": "ZIL_130_ac40_doors_codriver_cdf",
      "MaxPriceThreshold": 5000,
      "MinPriceThreshold": 5000,
      "SellPricePercent": 50.0,
      "MaxStockThreshold": 1,
      "MinStockThreshold": 1,
      "QuantityPercent": -1,
      "SpawnAttachments": [],
      "Variants": []
    },
    {
      "ClassName": "ZIL_130_ac40_doors_driver",
      "MaxPriceThreshold": 5000,
      "MinPriceThreshold": 5000,
      "SellPricePercent": 50.0,
      "MaxStockThreshold": 1,
      "MinStockThreshold": 1,
      "QuantityPercent": -1,
      "SpawnAttachments": [],
      "Variants": []
    },
    {
      "ClassName": "ZIL_130_ac40_doors_driver_CHAES",
      "MaxPriceThreshold": 5000,
      "MinPriceThreshold": 5000,
      "SellPricePercent": 50.0,
      "MaxStockThreshold": 1,
      "MinStockThreshold": 1,
      "QuantityPercent": -1,
      "SpawnAttachments": [],
      "Variants": []
    },
    {
      "ClassName": "ZIL_130_ac40_doors_driver_Chernobyl",
      "MaxPriceThreshold": 5000,
      "MinPriceThreshold": 5000,
      "SellPricePercent": 50.0,
      "MaxStockThreshold": 1,
      "MinStockThreshold": 1,
      "QuantityPercent": -1,
      "SpawnAttachments": [],
      "Variants": []
    },
    {
      "ClassName": "ZIL_130_ac40_doors_driver_Livonia",
      "MaxPriceThreshold": 5000,
      "MinPriceThreshold": 5000,
      "SellPricePercent": 50.0,
      "MaxStockThreshold": 1,
      "MinStockThreshold": 1,
      "QuantityPercent": -1,
      "SpawnAttachments": [],
      "Variants": []
    },
    {
      "ClassName": "ZIL_130_ac40_doors_driver_Pripyat",
      "MaxPriceThreshold": 5000,
      "MinPriceThreshold": 5000,
      "SellPricePercent": 50.0,
      "MaxStockThreshold": 1,
      "MinStockThreshold": 1,
      "QuantityPercent": -1,
      "SpawnAttachments": [],
      "Variants": []
    },
    {
      "ClassName": "ZIL_130_ac40_doors_hood",
      "MaxPriceThreshold": 5000,
      "MinPriceThreshold": 5000,
      "SellPricePercent": 50.0,
      "MaxStockThreshold": 1,
      "MinStockThreshold": 1,
      "QuantityPercent": -1,
      "SpawnAttachments": [],
      "Variants": []
    },
	{
      "ClassName": "ZIL_130_ac40_doors_hood_cdf",
      "MaxPriceThreshold": 5000,
      "MinPriceThreshold": 5000,
      "SellPricePercent": 50.0,
      "MaxStockThreshold": 1,
      "MinStockThreshold": 1,
      "QuantityPercent": -1,
      "SpawnAttachments": [],
      "Variants": []
    },
    {
      "ClassName": "ZIL_130_ac40_doors_trunk",
      "MaxPriceThreshold": 5000,
      "MinPriceThreshold": 5000,
      "SellPricePercent": 50.0,
      "MaxStockThreshold": 1,
      "MinStockThreshold": 1,
      "QuantityPercent": -1,
      "SpawnAttachments": [],
      "Variants": []
    },
    {
      "ClassName": "ZIL_130_ac40_wheel",
      "MaxPriceThreshold": 5000,
      "MinPriceThreshold": 5000,
      "SellPricePercent": 50.0,
      "MaxStockThreshold": 1,
      "MinStockThreshold": 1,
      "QuantityPercent": -1,
      "SpawnAttachments": [],
      "Variants": []
    },
    {
      "ClassName": "ZIL_130_ac40_WheelDouble",
      "MaxPriceThreshold": 5000,
      "MinPriceThreshold": 5000,
      "SellPricePercent": 50.0,
      "MaxStockThreshold": 1,
      "MinStockThreshold": 1,
      "QuantityPercent": -1,
      "SpawnAttachments": [],
      "Variants": []
    },
    {
      "ClassName": "ZIL_130_doors_codriver",
      "MaxPriceThreshold": 5000,
      "MinPriceThreshold": 5000,
      "SellPricePercent": 50.0,
      "MaxStockThreshold": 1,
      "MinStockThreshold": 1,
      "QuantityPercent": -1,
      "SpawnAttachments": [],
      "Variants": []
    },
	{
      "ClassName": "ZIL_130_doors_codriver_cdf",
      "MaxPriceThreshold": 5000,
      "MinPriceThreshold": 5000,
      "SellPricePercent": 50.0,
      "MaxStockThreshold": 1,
      "MinStockThreshold": 1,
      "QuantityPercent": -1,
      "SpawnAttachments": [],
      "Variants": []
    },
    {
      "ClassName": "ZIL_130_doors_codriver_green",
      "MaxPriceThreshold": 5000,
      "MinPriceThreshold": 5000,
      "SellPricePercent": 50.0,
      "MaxStockThreshold": 1,
      "MinStockThreshold": 1,
      "QuantityPercent": -1,
      "SpawnAttachments": [],
      "Variants": []
    },
    {
      "ClassName": "ZIL_130_doors_driver",
      "MaxPriceThreshold": 5000,
      "MinPriceThreshold": 5000,
      "SellPricePercent": 50.0,
      "MaxStockThreshold": 1,
      "MinStockThreshold": 1,
      "QuantityPercent": -1,
      "SpawnAttachments": [],
      "Variants": []
    },
	 {
      "ClassName": "ZIL_130_doors_driver_cdf",
      "MaxPriceThreshold": 5000,
      "MinPriceThreshold": 5000,
      "SellPricePercent": 50.0,
      "MaxStockThreshold": 1,
      "MinStockThreshold": 1,
      "QuantityPercent": -1,
      "SpawnAttachments": [],
      "Variants": []
    },
    {
      "ClassName": "ZIL_130_doors_driver_green",
      "MaxPriceThreshold": 5000,
      "MinPriceThreshold": 5000,
      "SellPricePercent": 50.0,
      "MaxStockThreshold": 1,
      "MinStockThreshold": 1,
      "QuantityPercent": -1,
      "SpawnAttachments": [],
      "Variants": []
    },
    {
      "ClassName": "ZIL_130_doors_hood",
      "MaxPriceThreshold": 5000,
      "MinPriceThreshold": 5000,
      "SellPricePercent": 50.0,
      "MaxStockThreshold": 1,
      "MinStockThreshold": 1,
      "QuantityPercent": -1,
      "SpawnAttachments": [],
      "Variants": []
    },
	{
      "ClassName": "ZIL_130_doors_hood_cdf",
      "MaxPriceThreshold": 5000,
      "MinPriceThreshold": 5000,
      "SellPricePercent": 50.0,
      "MaxStockThreshold": 1,
      "MinStockThreshold": 1,
      "QuantityPercent": -1,
      "SpawnAttachments": [],
      "Variants": []
    },
    {
      "ClassName": "ZIL_130_doors_hood_green",
      "MaxPriceThreshold": 5000,
      "MinPriceThreshold": 5000,
      "SellPricePercent": 50.0,
      "MaxStockThreshold": 1,
      "MinStockThreshold": 1,
      "QuantityPercent": -1,
      "SpawnAttachments": [],
      "Variants": []
    },
    {
      "ClassName": "ZIL_130_doors_trunk",
      "MaxPriceThreshold": 5000,
      "MinPriceThreshold": 5000,
      "SellPricePercent": 50.0,
      "MaxStockThreshold": 1,
      "MinStockThreshold": 1,
      "QuantityPercent": -1,
      "SpawnAttachments": [],
      "Variants": []
    },
    {
      "ClassName": "ZIL_130_tent",
      "MaxPriceThreshold": 5000,
      "MinPriceThreshold": 5000,
      "SellPricePercent": 50.0,
      "MaxStockThreshold": 1,
      "MinStockThreshold": 1,
      "QuantityPercent": -1,
      "SpawnAttachments": [],
      "Variants": []
    },
    {
      "ClassName": "ZIL_130_wheel",
      "MaxPriceThreshold": 5000,
      "MinPriceThreshold": 5000,
      "SellPricePercent": 50.0,
      "MaxStockThreshold": 1,
      "MinStockThreshold": 1,
      "QuantityPercent": -1,
      "SpawnAttachments": [],
      "Variants": []
    },
    {
      "ClassName": "ZIL_130_WheelDouble",
      "MaxPriceThreshold": 5000,
      "MinPriceThreshold": 5000,
      "SellPricePercent": 50.0,
      "MaxStockThreshold": 1,
      "MinStockThreshold": 1,
      "QuantityPercent": -1,
      "SpawnAttachments": [],
      "Variants": []
    }
    ]
}